population_trend/__init__.py
population_trend/calculate_growth_rates.py
population_trend/cli.py
population_trend/filter_data.py
population_trend/plotter_growth_rate.py
population_trend/plotter_population_trend_from_cpue.py
population_trend/population_growth_model.py
population_trend/regional_lambdas.py
population_trend-5.9.1.dist-info/entry_points.txt
population_trend-5.9.1.dist-info/LICENSE
population_trend-5.9.1.dist-info/WHEEL
population_trend-5.9.1.dist-info/METADATA
population_trend-5.9.1.dist-info/RECORD
