Metadata-Version: 2.1
Name: population_trend
Version: 5.9.1
Summary: A population growth model package
Home-page: https://github.com/IslasGECI/population_trend
Author: Ciencia de Datos • GECI
Author-email: ciencia.datos@islas.org.mx
Requires-Python: >=3.9
Classifier: License :: OSI Approved :: GNU General Public License v3 or later (GPLv3+)
Requires-Dist: bootstrapping-tools==3.*
Requires-Dist: geci-plots
Requires-Dist: typer[all]
